lingua_sql/__init__.py
lingua_sql/cli.py
lingua_sql/config.py
lingua_sql/intelligent_training.py
lingua_sql/agents/__init__.py
lingua_sql/base/base.py
lingua_sql/base/llm_base.py
lingua_sql/base/vector_base.py
lingua_sql/chromadb/chromadb_vector.py
lingua_sql/database/connection_factory.py
lingua_sql/database/ddl_extractor.py
lingua_sql/database/mysql_connector.py
lingua_sql/deepseek/deepseek_chat.py
lingua_sql/ernie/ernie_chat.py
lingua_sql/faiss/faiss_vector.py
lingua_sql/fastapi/__init__.py
lingua_sql/fastapi/app.py
lingua_sql/fastapi/cache.py
lingua_sql/fastapi/static/Lingua_sql.png
lingua_sql/fastapi/static/index.html
lingua_sql/fastapi/static/assets/css/index.css
lingua_sql/fastapi/static/assets/js/index.js
lingua_sql/fastapi/static/assets/js/index_beautified.js
lingua_sql/glm/glm_chat.py
lingua_sql/moonshot/moonshot_chat.py
lingua_sql/prompts/__init__.py
lingua_sql/prompts/intelligent_training_prompts.py
lingua_sql/prompts/training_config.py
lingua_sql/qwen/qwen_chat.py
lingua_sql/yi/yi_chat.py
lingua_sql-0.2.2.dist-info/METADATA
lingua_sql-0.2.2.dist-info/WHEEL
lingua_sql-0.2.2.dist-info/entry_points.txt
lingua_sql-0.2.2.dist-info/licenses/LICENSE
lingua_sql-0.2.2.dist-info/RECORD
