Metadata-Version: 2.4
Name: lingua-sql
Version: 0.2.2
Summary: 面向中文优化的 Text-to-SQL 系统，支持 FastAPI Web 界面、多种大语言模型和向量数据库（需要 Python 3.12）
Project-URL: Homepage, https://github.com/yin xu/lingua-sql
Project-URL: Documentation, https://lingua-sql.readthedocs.io/
Project-URL: Repository, https://github.com/yinxu-4869/lingua-sql
Project-URL: Bug Tracker, https://github.com/4869-yinxu/lingua-sql/issues
Project-URL: Changelog, https://github.com/4869-yinxu/lingua-sql/blob/main/CHANGELOG.md
Author-email: 殷旭 <2337302325@qq.com>
License: MIT
License-File: LICENSE
Keywords: ai,chinese,chromadb,database,deepseek,fastapi,llm,nlp,text-to-sql,vector-database
Classifier: Development Status :: 4 - Beta
Classifier: Framework :: FastAPI
Classifier: Intended Audience :: Developers
Classifier: Intended Audience :: Science/Research
Classifier: License :: OSI Approved :: MIT License
Classifier: Operating System :: OS Independent
Classifier: Programming Language :: Python :: 3
Classifier: Programming Language :: Python :: 3.12
Classifier: Topic :: Database
Classifier: Topic :: Internet :: WWW/HTTP :: HTTP Servers
Classifier: Topic :: Scientific/Engineering :: Artificial Intelligence
Classifier: Topic :: Software Development :: Libraries :: Python Modules
Classifier: Topic :: Text Processing :: Linguistic
Requires-Python: ~=3.12.0
Requires-Dist: chromadb>=0.4.22
Requires-Dist: fastapi>=0.109.0
Requires-Dist: httpx>=0.27.0
Requires-Dist: jinja2>=3.1.0
Requires-Dist: mysql-connector-python>=8.0.0
Requires-Dist: openai>=1.12.0
Requires-Dist: pandas>=2.0.0
Requires-Dist: plotly>=5.18.0
Requires-Dist: pydantic>=2.6.0
Requires-Dist: python-dotenv>=1.0.0
Requires-Dist: python-multipart>=0.0.6
Requires-Dist: requests>=2.31.0
Requires-Dist: sqlparse>=0.4.4
Requires-Dist: streamlit>=1.32.0
Requires-Dist: uvicorn>=0.27.0
Provides-Extra: dev
Requires-Dist: black>=23.0.0; extra == 'dev'
Requires-Dist: flake8>=6.0.0; extra == 'dev'
Requires-Dist: isort>=5.12.0; extra == 'dev'
Requires-Dist: mypy>=1.0.0; extra == 'dev'
Requires-Dist: pytest-cov>=4.0.0; extra == 'dev'
Requires-Dist: pytest>=7.0.0; extra == 'dev'
Provides-Extra: docs
Requires-Dist: myst-parser>=2.0.0; extra == 'docs'
Requires-Dist: sphinx-rtd-theme>=1.3.0; extra == 'docs'
Requires-Dist: sphinx>=7.0.0; extra == 'docs'
